{
    "fluentMethods": true,
    "relationships": [
        {
            "relationshipType": "one-to-many",
            "relationshipName": "datlab",
            "otherEntityName": "datlab",
            "otherEntityRelationshipName": "modcontrato"
        }
    ],
    "fields": [
        {
            "fieldName": "vDesmodcon",
            "javadoc": "DESCRIPCION DE LA MODALIDAD DE CONTRATO.",
            "fieldType": "String",
            "fieldValidateRules": [
                "required",
                "maxlength"
            ],
            "fieldValidateRulesMaxlength": 200
        },
        {
            "fieldName": "nUsuareg",
            "javadoc": "CODIGO DEL USUARIO QUE REGISTRA.",
            "fieldType": "Integer",
            "fieldValidateRules": [
                "required"
            ]
        },
        {
            "fieldName": "tFecreg",
            "javadoc": "FECHA Y HORA DEL REGISTRO.",
            "fieldType": "Instant",
            "fieldValidateRules": [
                "required"
            ]
        },
        {
            "fieldName": "nFlgactivo",
            "javadoc": "ESTADO ACTIVO DEL REGISTRO (1=ACTIVO, 0=INACTIVO)",
            "fieldType": "Boolean",
            "fieldValidateRules": [
                "required"
            ]
        },
        {
            "fieldName": "nSedereg",
            "javadoc": "CODIGO DE LA SEDE DONDE SE REGISTRA.",
            "fieldType": "Integer",
            "fieldValidateRules": [
                "required"
            ]
        },
        {
            "fieldName": "nUsuaupd",
            "javadoc": "CODIGO DEL USUARIO QUE MODIFICA EL REGISTRO.",
            "fieldType": "Integer"
        },
        {
            "fieldName": "tFecupd",
            "javadoc": "CODIGO DEL USUARIO QUE MODIFICA EL REGISTRO.",
            "fieldType": "Instant"
        },
        {
            "fieldName": "nSedeupd",
            "javadoc": "CODIGO DE LA SEDE DONDE SE MODIFICA EL REGISTRO.",
            "fieldType": "Integer"
        }
    ],
    "changelogDate": "20171125013908",
    "javadoc": "LISTA MAESTRA DE MODALIDADES DE CONTRATO",
    "entityTableName": "modcontrato",
    "dto": "no",
    "pagination": "no",
    "service": "no"
}